eitaa/__init__.py
eitaa_pykit-1.2.1.dist-info/LICENSE
eitaa_pykit-1.2.1.dist-info/METADATA
eitaa_pykit-1.2.1.dist-info/WHEEL
eitaa_pykit-1.2.1.dist-info/top_level.txt
eitaa_pykit-1.2.1.dist-info/RECORD
