Metadata-Version: 2.1
Name: eitaa-pykit
Version: 1.2.1
Summary: UNKNOWN
Home-page: https://github.com/bistcuite/eitaapykit
License: UNKNOWN
Platform: UNKNOWN
License-File: LICENSE
Requires-Dist: requests
Requires-Dist: bs4
